JoyIT_hx711py/JoyIT_hx711py.py
JoyIT_hx711py/__init__.py
JoyIT_hx711py-0.1.1.dist-info/LICENSE
JoyIT_hx711py-0.1.1.dist-info/METADATA
JoyIT_hx711py-0.1.1.dist-info/WHEEL
JoyIT_hx711py-0.1.1.dist-info/top_level.txt
JoyIT_hx711py-0.1.1.dist-info/RECORD
