Metadata-Version: 2.1
Name: JoyIT-hx711py
Version: 0.1.1
Summary: Updated Python library for the HX711 load cell amplifier and Raspberry Pi 5
Home-page: https://github.com/joy-it/JoyIT_hx711py
Author: j-dohnalek
Author-email: service@joy-it.net
License: UNKNOWN
Platform: UNKNOWN
Classifier: Programming Language :: Python :: 3
Classifier: License :: OSI Approved :: GNU General Public License v2 (GPLv2)
Requires-Python: >=3.6
License-File: LICENSE
